SMjournal/__init__.py
SMjournal/collinearity.py
SMjournal/data.py
SMjournal/low_level.py
SMjournal/meta_reg.py
SMjournal/potentiality.py
SMjournal-0.0.24.dist-info/LICENSE
SMjournal-0.0.24.dist-info/METADATA
SMjournal-0.0.24.dist-info/WHEEL
SMjournal-0.0.24.dist-info/top_level.txt
SMjournal-0.0.24.dist-info/RECORD
